Workbook

Sheet 物料台账
A1: 2025 年度备件采购台账
A2: 编制部门: 设备动力部
A3: 物料编码 | B3: 物料名称 | C3: 单价(元) | D3: 数量 | E3: 金额(元) | F3: 含税金额 | G3: 等级 | H3: 数量级别 | I3: 累计金额 | J3: 折扣 | K3: 折后金额 | L3: 单价级别
A4: M-01 | B4: 深沟球轴承 6204 | C4: 32.5 | D4: 120 | E4: =ROUND(C4*D4,2) | F4: =ROUND(E4*1.13,2) | G4: =IFERROR(VLOOKUP(A4,等级表!$A$2:$C$7,2,FALSE),"未登记") | H4: =IFS(D4>=100,"大批量",D4>=50,"中批量",TRUE,"小批量") | I4: =ROUND(SUM($E$4:E4),2) | J4: =IFERROR(INDEX(等级表!$C$2:$C$7,MATCH(A4,等级表!$A$2:$A$7,0)),1) | K4: =ROUND(E4*J4,2) | L4: =IF(C4>=100,"高",IF(C4>=50,"中","低"))
A5: M-02 | B5: 不锈钢内六角螺栓 M8 | C5: 1.85 | D5: 500 | E5: =ROUND(C5*D5,2) | F5: =ROUND(E5*1.13,2) | G5: =IFERROR(VLOOKUP(A5,等级表!$A$2:$C$7,2,FALSE),"未登记") | H5: =IFS(D5>=100,"大批量",D5>=50,"中批量",TRUE,"小批量") | I5: =ROUND(SUM($E$4:E5),2) | J5: =IFERROR(INDEX(等级表!$C$2:$C$7,MATCH(A5,等级表!$A$2:$A$7,0)),1) | K5: =ROUND(E5*J5,2) | L5: =IF(C5>=100,"高",IF(C5>=50,"中","低"))
A6: M-03 | B6: 液压油 46# | C6: 28 | D6: 60 | E6: =ROUND(C6*D6,2) | F6: =ROUND(E6*1.13,2) | G6: =IFERROR(VLOOKUP(A6,等级表!$A$2:$C$7,2,FALSE),"未登记") | H6: =IFS(D6>=100,"大批量",D6>=50,"中批量",TRUE,"小批量") | I6: =ROUND(SUM($E$4:E6),2) | J6: =IFERROR(INDEX(等级表!$C$2:$C$7,MATCH(A6,等级表!$A$2:$A$7,0)),1) | K6: =ROUND(E6*J6,2) | L6: =IF(C6>=100,"高",IF(C6>=50,"中","低"))
A7: M-04 | B7: 同步带 5M-450 | C7: 46.2 | D7: 35 | E7: =ROUND(C7*D7,2) | F7: =ROUND(E7*1.13,2) | G7: =IFERROR(VLOOKUP(A7,等级表!$A$2:$C$7,2,FALSE),"未登记") | H7: =IFS(D7>=100,"大批量",D7>=50,"中批量",TRUE,"小批量") | I7: =ROUND(SUM($E$4:E7),2) | J7: =IFERROR(INDEX(等级表!$C$2:$C$7,MATCH(A7,等级表!$A$2:$A$7,0)),1) | K7: =ROUND(E7*J7,2) | L7: =IF(C7>=100,"高",IF(C7>=50,"中","低"))
A8: M-05 | B8: 气动电磁阀 4V210 | C8: 118 | D8: 24 | E8: =ROUND(C8*D8,2) | F8: =ROUND(E8*1.13,2) | G8: =IFERROR(VLOOKUP(A8,等级表!$A$2:$C$7,2,FALSE),"未登记") | H8: =IFS(D8>=100,"大批量",D8>=50,"中批量",TRUE,"小批量") | I8: =ROUND(SUM($E$4:E8),2) | J8: =IFERROR(INDEX(等级表!$C$2:$C$7,MATCH(A8,等级表!$A$2:$A$7,0)),1) | K8: =ROUND(E8*J8,2) | L8: =IF(C8>=100,"高",IF(C8>=50,"中","低"))
A9: M-06 | B9: PLC 扩展模块 FX2N-16EX | C9: 385 | D9: 12 | E9: =ROUND(C9*D9,2) | F9: =ROUND(E9*1.13,2) | G9: =IFERROR(VLOOKUP(A9,等级表!$A$2:$C$7,2,FALSE),"未登记") | H9: =IFS(D9>=100,"大批量",D9>=50,"中批量",TRUE,"小批量") | I9: =ROUND(SUM($E$4:E9),2) | J9: =IFERROR(INDEX(等级表!$C$2:$C$7,MATCH(A9,等级表!$A$2:$A$7,0)),1) | K9: =ROUND(E9*J9,2) | L9: =IF(C9>=100,"高",IF(C9>=50,"中","低"))
A10: M-08 | B10: 接近开关 LJ12A3 | C10: 42 | D10: 90 | E10: =ROUND(C10*D10,2) | F10: =ROUND(E10*1.13,2) | G10: =IFERROR(VLOOKUP(A10,等级表!$A$2:$C$7,2,FALSE),"未登记") | H10: =IFS(D10>=100,"大批量",D10>=50,"中批量",TRUE,"小批量") | I10: =ROUND(SUM($E$4:E10),2) | J10: =IFERROR(INDEX(等级表!$C$2:$C$7,MATCH(A10,等级表!$A$2:$A$7,0)),1) | K10: =ROUND(E10*J10,2) | L10: =IF(C10>=100,"高",IF(C10>=50,"中","低"))
A11: M-09 | B11: 变频器 VFD-M 2.2KW | C11: 1560 | D11: 6 | E11: =ROUND(C11*D11,2) | F11: =ROUND(E11*1.13,2) | G11: =IFERROR(VLOOKUP(A11,等级表!$A$2:$C$7,2,FALSE),"未登记") | H11: =IFS(D11>=100,"大批量",D11>=50,"中批量",TRUE,"小批量") | I11: =ROUND(SUM($E$4:E11),2) | J11: =IFERROR(INDEX(等级表!$C$2:$C$7,MATCH(A11,等级表!$A$2:$A$7,0)),1) | K11: =ROUND(E11*J11,2) | L11: =IF(C11>=100,"高",IF(C11>=50,"中","低"))
A12: M-10 | B12: 耐油橡胶垫 3mm | C12: 15.5 | D12: 200 | E12: =ROUND(C12*D12,2) | F12: =ROUND(E12*1.13,2) | G12: =IFERROR(VLOOKUP(A12,等级表!$A$2:$C$7,2,FALSE),"未登记") | H12: =IFS(D12>=100,"大批量",D12>=50,"中批量",TRUE,"小批量") | I12: =ROUND(SUM($E$4:E12),2) | J12: =IFERROR(INDEX(等级表!$C$2:$C$7,MATCH(A12,等级表!$A$2:$A$7,0)),1) | K12: =ROUND(E12*J12,2) | L12: =IF(C12>=100,"高",IF(C12>=50,"中","低"))
A13: M-12 | B13: 时间继电器 ST3PA-B | C13: 68 | D13: 45 | E13: =ROUND(C13*D13,2) | F13: =ROUND(E13*1.13,2) | G13: =IFERROR(VLOOKUP(A13,等级表!$A$2:$C$7,2,FALSE),"未登记") | H13: =IFS(D13>=100,"大批量",D13>=50,"中批量",TRUE,"小批量") | I13: =ROUND(SUM($E$4:E13),2) | J13: =IFERROR(INDEX(等级表!$C$2:$C$7,MATCH(A13,等级表!$A$2:$A$7,0)),1) | K13: =ROUND(E13*J13,2) | L13: =IF(C13>=100,"高",IF(C13>=50,"中","低"))
A15: 金额合计 | C15: =ROUND(SUM(E4:E13),2)
A16: 含税合计 | C16: =ROUND(SUM(F4:F13),2)
A17: 平均单价 | C17: =ROUND(AVERAGE(C4:C13),2)
A18: 最大/最小金额 | C18: =ROUND(MAX(E4:E13)-MIN(E4:E13),2)
A19: 金额中位数 | C19: =ROUND(MEDIAN(E4:E13),2)
A20: 加权平均单价(SUMPRODUCT) | C20: =ROUND(SUMPRODUCT(C4:C13,D4:D13)/SUM(D4:D13),2)
A21: 数量≥50 金额合计(SUMIF) | C21: =ROUND(SUMIF(D4:D13,">=50",E4:E13),2)
A22: 等级=A 金额合计(SUMIFS) | C22: =ROUND(SUMIFS(E4:E13,G4:G13,"A"),2)
A23: 等级=A 平均金额(AVERAGEIFS) | C23: =ROUND(AVERAGEIFS(E4:E13,G4:G13,"A"),2)
A24: 最大单笔(MAXIFS) | C24: =MAXIFS(E4:E13,D4:D13,">=50")
A25: 最小单笔(MINIFS) | C25: =MINIFS(E4:E13,D4:D13,">=50")
A26: 第 2 高金额(LARGE) | C26: =LARGE(E4:E13,2)
A27: 第 3 低金额(SMALL) | C27: =SMALL(E4:E13,3)
A28: M-05 金额排名(RANK) | C28: =RANK(INDEX(E4:E13,MATCH("M-05",A4:A13,0)),E4:E13)
A29: 金额标准差(STDEV) | C29: =ROUND(STDEV(E4:E13),2)
A30: 90 分位(PERCENTILE) | C30: =ROUND(PERCENTILE(E4:E13,0.9),2)
A31: 单价>50 种类(COUNTIF) | C31: =COUNTIF(C4:C13,">50")
A32: 非 A 级数量(COUNTIF <>) | C32: =COUNTIF(G4:G13,"<>A")
A33: M-07 名称(XLOOKUP 默认值) | C33: =XLOOKUP("M-07",A4:A13,B4:B13,"无此物料")
A34: M-06 名称(INDEX+MATCH) | C34: =INDEX(B4:B13,MATCH("M-06",A4:A13,0))
A35: 前 5 行金额(SUM+OFFSET) | C35: =ROUND(SUM(OFFSET(E4,0,0,5,1)),2)
A36: 明细行数(ROWS) | C36: =ROWS(A4:A13)
A37: 月供测算(PMT) | C37: =ROUND(PMT(0.05/12,36,60000),2)
A38: 前 4 笔净现值(NPV) | C38: =ROUND(NPV(0.08,E4:E7),2)
A39: 月份文本(TEXT) | C39: =TEXT(DATE(2025,3,1),"yyyy年m月")
A40: 除零兜底(IFERROR) | C40: =IFERROR(1/0,"已兜底")
A41: 查无编码(IFNA) | C41: =IFNA(VLOOKUP("M-99",A4:C13,2,FALSE),"查无编码")

Sheet 等级表
A1: 物料编码 | B1: 等级 | C1: 折扣
A2: M-01 | B2: A | C2: 0.97
A3: M-02 | B3: B | C3: 1
A4: M-03 | B4: B | C4: 1
A5: M-04 | B5: C | C5: 1.05
A6: M-05 | B6: A | C6: 0.95
A7: M-06 | B7: A | C7: 0.92

Sheet 统计
A1: 项目 | B1: 值 | C1: 备注
A2: 合同起始日 | B2: 45733
A3: 合同到期日 | B3: 46053
A4: 合同天数(DAYS) | B4: =DAYS(B3,B2) | C4: 日历天数
A5: 工作日数(NETWORKDAYS) | B5: =NETWORKDAYS(B2,B3) | C5: 排除周末
A6: 3 个月后月末(EOMONTH) | B6: =EOMONTH(B2,3) | C6: 日期序列
A7: 到期前 45 个工作日(WORKDAY) | B7: =WORKDAY(B2,45) | C7: 工期推算
A8: 已执行年数(DATEDIF Y) | B8: =DATEDIF(B2,B3,"Y") | C8: 整年
A9: 已执行月数(DATEDIF M) | B9: =DATEDIF(B2,B3,"M") | C9: 整月
A10: 起始年份(YEAR) | B10: =YEAR(B2)
A11: 起始月份(MONTH) | B11: =MONTH(B2)
A12: 起始日(WEEKDAY) | B12: =WEEKDAY(B2,2) | C12: 周一=1
A13: 月份文本(TEXT) | B13: =TEXT(B2,"yyyy年m月")
A14: 拼接(TEXTJOIN) | B14: =TEXTJOIN("-",TRUE,"合同",B4,"天")
A15: 金额平方和(SUMSQ) | B15: =ROUND(SUMSQ(物料台账!E4:E13),2)
A16: 单价几何均值(GEOMEAN 不支持→SQRT) | B16: =ROUND(SQRT(PRODUCT(物料台账!C4:C6)),2) | C16: 乘积开方
A17: 金额取整(CEILING) | B17: =CEILING(物料台账!E4,10)
A18: 金额截断(TRUNC) | B18: =TRUNC(物料台账!E4,0)
A19: 单价四舍五入到角(MROUND) | B19: =MROUND(物料台账!C5,0.1)
A20: 金额符号(SIGN) | B20: =SIGN(物料台账!E4-1000) | C20: 正=1 负=-1
A21: 编号示例(REPT/PROPER) | B21: =PROPER("no.")&REPT("0",3)&"7"
A22: 查字符(CHAR 65) | B22: =CHAR(65)
A23: 字符码(CODE A) | B23: =CODE("A")
A24: 文本转数值(VALUE) | B24: =VALUE("¥1,234.50")
A25: 首段文本(FIND/LEFT) | B25: =LEFT(物料台账!B4,FIND(" ",物料台账!B4)-1)

Sheet 说明
A1: 本文件由 openpyxl 生成, 公式无缓存值 —— 用于验证 office rag prep 的内置求值器。
A2: 数组表达式(如 SUMPRODUCT((条件)*(区域)))不在支持范围, 预期记为 formula_unresolved。
